cenzopapa/__init__.py
cenzopapa/exceptions.py
cenzopapa/mixins.py
cenzopapa/resource_client.py
cenzopapa/resources.py
cenzopapa/schemas.py
cenzopapa_sdk-1.1.1.dist-info/METADATA
cenzopapa_sdk-1.1.1.dist-info/WHEEL
cenzopapa_sdk-1.1.1.dist-info/top_level.txt
cenzopapa_sdk-1.1.1.dist-info/RECORD
